quart_oauth2_discord_py/__init__.py
quart_oauth2_discord_py/base.py
quart_oauth2_discord_py/client.py
quart_oauth2_discord_py/exceptions.py
quart_oauth2_discord_py/http.py
quart_oauth2_discord_py/models/__init__.py
quart_oauth2_discord_py/models/guild.py
quart_oauth2_discord_py/models/user.py
quart_oauth2_discord.py-0.1.0.dist-info/WHEEL
quart_oauth2_discord.py-0.1.0.dist-info/METADATA
quart_oauth2_discord.py-0.1.0.dist-info/RECORD
