Metadata-Version: 2.1
Name: quart-oauth2-discord.py
Version: 0.1.0
Summary: A library to make the discord authentication system easier for Quart Users
License: MIT
Author: sairam4123
Author-email: sairamkumar2022@gmail.com
Requires-Python: >=3.9,<4.0
Classifier: Development Status :: 4 - Beta
Classifier: Environment :: Web Environment
Classifier: Intended Audience :: Developers
Classifier: License :: OSI Approved :: MIT License
Classifier: Natural Language :: English
Classifier: Operating System :: OS Independent
Classifier: Programming Language :: Python :: 3
Classifier: Programming Language :: Python :: 3.9
Classifier: Topic :: Internet :: WWW/HTTP :: Dynamic Content
Classifier: Topic :: Software Development :: Libraries :: Python Modules
Requires-Dist: aiohttp (>=3.6.2,<4.0.0)
Requires-Dist: authlib (>=0.14.3,<0.15.0)
Requires-Dist: httpx (>=0.15.4,<0.16.0)
Requires-Dist: quart (>=0.13.1,<0.14.0)
